bonfig/__init__.py
bonfig/core.py
bonfig/fields.py
bonfig-0.2.2.dist-info/LICENSE.txt
bonfig-0.2.2.dist-info/WHEEL
bonfig-0.2.2.dist-info/METADATA
bonfig-0.2.2.dist-info/RECORD
