Metadata-Version: 2.1
Name: bonfig
Version: 0.2.2
Summary: Don't write configurations, write class declarations.
Home-page: https://github.com/0Hughman0/bonfig
License: MIT
Keywords: configuration,inheritance,OOP
Author: 0Hughman0
Author-email: rammers2@hotmail.co.uk
Requires-Python: >=3.4,<4.0
Classifier: License :: OSI Approved :: MIT License
Classifier: Programming Language :: Python :: 3
Classifier: Programming Language :: Python :: 3.4
Classifier: Programming Language :: Python :: 3.5
Classifier: Programming Language :: Python :: 3.6
Classifier: Programming Language :: Python :: 3.7
Project-URL: Documentation, https://0hughman0.github.io/bonfig/index.html
